LICENSE.txt
README.md
setup.cfg
setup.py
mushroom/__init__.py
mushroom/arg_builder.py
mushroom/arg_exceptions.py
mushroom/arg_textwrap.py
mushroom/args_fetch.py
mushroom/core.py
mushroom/extra_functools.py
mushroom/func_parser.py
mushroom/traceback_module.py
mushroom/traceback_terminal.py
mushroom_cli.egg-info/PKG-INFO
mushroom_cli.egg-info/SOURCES.txt
mushroom_cli.egg-info/dependency_links.txt
mushroom_cli.egg-info/not-zip-safe
mushroom_cli.egg-info/top_level.txt