Metadata-Version: 2.1
Name: mushroom-cli
Version: 0.3.6
Summary: This is a library for generating the command line interfaces for python scripts.
Author: Asriel
Author-email: sariellian@icloud.com
License: MIT
Platform: any
License-File: LICENSE.txt
